gnuxlinux/__init__.py
gnuxlinux/__main__.py
gnuxlinux/api/__init__.py
gnuxlinux/api/base.py
gnuxlinux/api/utils.py
gnuxlinux/features/slug.py
gnuxlinux/cat.cpython-312-x86_64-linux-gnu.so
gnuxlinux/ext.cpython-312-x86_64-linux-gnu.so
gnuxlinux/mkdir.cpython-312-x86_64-linux-gnu.so
gnuxlinux-0.1.2.dist-info/LICENSE
gnuxlinux-0.1.2.dist-info/METADATA
gnuxlinux-0.1.2.dist-info/WHEEL
gnuxlinux-0.1.2.dist-info/entry_points.txt
gnuxlinux-0.1.2.dist-info/RECORD
